helloworld.py
helloworldNJohnson-0.0.1.dist-info/METADATA
helloworldNJohnson-0.0.1.dist-info/WHEEL
helloworldNJohnson-0.0.1.dist-info/top_level.txt
helloworldNJohnson-0.0.1.dist-info/RECORD
