Metadata-Version: 2.1
Name: helloworldNJohnson
Version: 0.0.1
Summary: Says Hello
License: UNKNOWN
Platform: UNKNOWN
